vallenae/__init__.py
vallenae/_numba.py
vallenae/py.typed
vallenae/_pyinstaller/__init__.py
vallenae/_pyinstaller/hook-vallenae.py
vallenae/_pyinstaller/test_pyinstaller_hook.py
vallenae/features/__init__.py
vallenae/features/acoustic_emission.py
vallenae/features/conversion.py
vallenae/io/__init__.py
vallenae/io/_database.py
vallenae/io/_dataframe.py
vallenae/io/_sql.py
vallenae/io/_types.py
vallenae/io/compression.py
vallenae/io/datatypes.py
vallenae/io/pridb.py
vallenae/io/tradb.py
vallenae/io/trfdb.py
vallenae/io/schema_templates/pridb.sql
vallenae/io/schema_templates/tradb.sql
vallenae/io/schema_templates/trfdb.sql
vallenae/timepicker/__init__.py
vallenae-0.13.0.dist-info/METADATA
vallenae-0.13.0.dist-info/WHEEL
vallenae-0.13.0.dist-info/entry_points.txt
vallenae-0.13.0.dist-info/licenses/LICENSE.txt
vallenae-0.13.0.dist-info/RECORD
