Metadata-Version: 2.4
Name: vallenae
Version: 0.13.0
Summary: Extract and analyze Acoustic Emission measurement data
Project-URL: Changelog, https://github.com/vallen-systems/pyVallenAE/blob/master/CHANGELOG.md
Project-URL: Source, https://github.com/vallen-systems/pyVallenAE
Project-URL: Issues, https://github.com/vallen-systems/pyVallenAE/issues
Author-email: Lukas Berbuer <software@vallen.de>
License: MIT License
License-File: LICENSE.txt
Keywords: acoustic emission,amsy,analysis,data acquisition,pridb,sqlite,timepicker,tradb,trfdb,vallen,waveline
Classifier: Development Status :: 4 - Beta
Classifier: Intended Audience :: Science/Research
Classifier: License :: OSI Approved :: MIT License
Classifier: Operating System :: OS Independent
Classifier: Programming Language :: Python :: 3
Classifier: Programming Language :: Python :: 3.7
Classifier: Programming Language :: Python :: 3.8
Classifier: Programming Language :: Python :: 3.9
Classifier: Programming Language :: Python :: 3.10
Classifier: Programming Language :: Python :: 3.11
Classifier: Programming Language :: Python :: 3.12
Classifier: Programming Language :: Python :: 3.13
Classifier: Programming Language :: Python :: 3.14
Classifier: Topic :: Scientific/Engineering
Classifier: Topic :: Software Development
Classifier: Topic :: Software Development :: Libraries
Requires-Python: >=3.7
Requires-Dist: numpy
Requires-Dist: pandas>=0.24
Requires-Dist: soundfile
Requires-Dist: tqdm
Requires-Dist: typing-extensions
Provides-Extra: dev
Requires-Dist: coverage[toml]>=5; extra == 'dev'
Requires-Dist: furo; extra == 'dev'
Requires-Dist: matplotlib; extra == 'dev'
Requires-Dist: mypy>=0.9; extra == 'dev'
Requires-Dist: myst-parser; extra == 'dev'
Requires-Dist: numba; extra == 'dev'
Requires-Dist: pillow; extra == 'dev'
Requires-Dist: pytest-benchmark; extra == 'dev'
Requires-Dist: pytest>=6; extra == 'dev'
Requires-Dist: ruff>=0.5; extra == 'dev'
Requires-Dist: scipy; extra == 'dev'
Requires-Dist: sphinx-autodoc-typehints; extra == 'dev'
Requires-Dist: sphinx-gallery; extra == 'dev'
Requires-Dist: sphinx>=5; extra == 'dev'
Requires-Dist: tox>=3.4; extra == 'dev'
Provides-Extra: docs
Requires-Dist: furo; extra == 'docs'
Requires-Dist: matplotlib; extra == 'docs'
Requires-Dist: myst-parser; extra == 'docs'
Requires-Dist: numba; extra == 'docs'
Requires-Dist: pillow; extra == 'docs'
Requires-Dist: scipy; extra == 'docs'
Requires-Dist: sphinx-autodoc-typehints; extra == 'docs'
Requires-Dist: sphinx-gallery; extra == 'docs'
Requires-Dist: sphinx>=5; extra == 'docs'
Provides-Extra: tests
Requires-Dist: coverage[toml]>=5; extra == 'tests'
Requires-Dist: pytest-benchmark; extra == 'tests'
Requires-Dist: pytest>=6; extra == 'tests'
Provides-Extra: tools
Requires-Dist: mypy>=0.9; extra == 'tools'
Requires-Dist: ruff>=0.5; extra == 'tools'
Requires-Dist: tox>=3.4; extra == 'tools'
